setup.py
wxgoodies/__init__.py
wxgoodies/keys.py
wxgoodies.egg-info/PKG-INFO
wxgoodies.egg-info/SOURCES.txt
wxgoodies.egg-info/dependency_links.txt
wxgoodies.egg-info/pbr.json
wxgoodies.egg-info/top_level.txt
wxgoodies.egg-info/zip-safe