Metadata-Version: 1.0
Name: wxgoodies
Version: 0.1
Summary: Helper functions for wxPython.
Home-page: https://github.com/chrisnorman7/wxgoodies
Author: Chris Norman
Author-email: chris.norman2@googlemail.com
License: GPL
Keywords: hotkeys
Platform: UNKNOWN
